setup.py
simplekit/__init__.py
simplekit.egg-info/PKG-INFO
simplekit.egg-info/SOURCES.txt
simplekit.egg-info/dependency_links.txt
simplekit.egg-info/not-zip-safe
simplekit.egg-info/top_level.txt
simplekit/objson/__init__.py
simplekit/objson/dolphin.py
simplekit/objson/dynamic_class.py