Metadata-Version: 1.1
Name: simplekit
Version: 0.0.4
Summary: A simple and brief utility tools framework
Home-page: https://github.com/by46/simplekit
Author: Benjamin Yan
Author-email: ycs_ctbu_2010@126.com
License: The MIT License
Platform: UNKNOWN
Classifier: Development Status :: 5 - Production/Stable
Classifier: Intended Audience :: Developers
Classifier: Natural Language :: English
Classifier: License :: OSI Approved :: MIT License
Classifier: Programming Language :: Python
Classifier: Programming Language :: Python :: 2.7
